tiled_convolution/__init__.py
tiled_convolution/functions.py
tiled_convolution-0.1.1.dist-info/METADATA
tiled_convolution-0.1.1.dist-info/WHEEL
tiled_convolution-0.1.1.dist-info/top_level.txt
tiled_convolution-0.1.1.dist-info/RECORD
